tests/__init__.py
yaratool/__init__.py
yaratool-0.0.7.dist-info/DESCRIPTION.rst
yaratool-0.0.7.dist-info/METADATA
yaratool-0.0.7.dist-info/RECORD
yaratool-0.0.7.dist-info/WHEEL
yaratool-0.0.7.dist-info/metadata.json
yaratool-0.0.7.dist-info/top_level.txt
