Metadata-Version: 2.0
Name: yaratool
Version: 0.0.7
Summary: Python libary to normalize Yara signatures
Home-page: https://github.com/chrislee35/yaratool
Author: Chris Lee & Friends
Author-email: python @ chrislee.dhs.org
License: BSD
Keywords: yara malware
Platform: UNKNOWN
Classifier: Development Status :: 3 - Alpha
Classifier: Topic :: Utilities
Classifier: License :: OSI Approved :: MIT License
